temporal_disagg/__init__.py
temporal_disagg/aggregation.py
temporal_disagg/base.py
temporal_disagg/conversion_matrix.py
temporal_disagg/estimation.py
temporal_disagg/optimization.py
temporal_disagg/preprocessing.py
temporal_disagg/retropolation.py
temporal_disagg/models/__init__.py
temporal_disagg/models/chow_lin.py
temporal_disagg/models/denton.py
temporal_disagg/models/denton_cholette.py
temporal_disagg/models/dynamic_models.py
temporal_disagg/models/fast.py
temporal_disagg/models/fernandez.py
temporal_disagg/models/litterman.py
temporal_disagg/models/ols.py
temporal_disagg/models/uniform.py
temporal_disagg-0.1.4.dist-info/licenses/LICENSE
temporal_disagg-0.1.4.dist-info/METADATA
temporal_disagg-0.1.4.dist-info/WHEEL
temporal_disagg-0.1.4.dist-info/top_level.txt
temporal_disagg-0.1.4.dist-info/RECORD
