Metadata-Version: 2.4
Name: temporal_disagg
Version: 0.1.4
Summary: Library for time series temporal disaggregation
Author-email: Jaime Vera-Jaramillo <jaimevera1107@gmail.com>
Requires-Python: >=3.9
License-File: LICENSE
Requires-Dist: numpy
Requires-Dist: pandas
Requires-Dist: scipy
Requires-Dist: joblib
Requires-Dist: matplotlib
Requires-Dist: scikit-learn
Dynamic: license-file
